refchef/__init__.py
refchef/config.py
refchef/github_utils.py
refchef/references.py
refchef/serve.py
refchef/table_utils.py
refchef/utils.py
refchef-1.0.1.data/scripts/refchef-cook
refchef-1.0.1.data/scripts/refchef-menu
refchef-1.0.1.data/scripts/refchef-serve
tests/__init__.py
tests/test_config.py
tests/test_github_utils.py
tests/test_references.py
tests/test_serve.py
tests/test_table_utils.py
tests/test_utils.py
refchef-1.0.1.dist-info/LICENSE
refchef-1.0.1.dist-info/METADATA
refchef-1.0.1.dist-info/WHEEL
refchef-1.0.1.dist-info/top_level.txt
refchef-1.0.1.dist-info/RECORD
