Metadata-Version: 2.1
Name: refchef
Version: 1.0.1
Summary: Genome reference manager.
Home-page: https://github.com/compbiocore/refchef
Author: Andrew Leith & Fernando Gelin
Author-email: cbc-help@brown.edu
License: UNKNOWN
Platform: UNKNOWN
Classifier: Programming Language :: Python :: 2
Classifier: Programming Language :: Python :: 3
Classifier: License :: OSI Approved :: GNU General Public License v3 or later (GPLv3+)
Classifier: Operating System :: MacOS
Classifier: Operating System :: Unix
Requires-Dist: argparse
Requires-Dist: flask
Requires-Dist: python-dotenv
Requires-Dist: oyaml
Requires-Dist: pygithub
Requires-Dist: yamlloader
Requires-Dist: pandas
Requires-Dist: terminaltables
Requires-Dist: mock
Requires-Dist: future
Requires-Dist: configparser
Requires-Dist: pytest (>=3.6)
Requires-Dist: coverage (>=4.4)
Requires-Dist: pytest-cov (>=2.0)
Requires-Dist: hiyapyco
